ip_reveal/.idea/.gitignore
ip_reveal/.idea/inspectionProfiles/profiles_settings.xml
ip_reveal/.idea/ip_reveal.iml
ip_reveal/.idea/misc.xml
ip_reveal/.idea/modules.xml
ip_reveal/.idea/vcs.xml
ip_reveal/__init__.py
ip_reveal/assets/__init__.py
ip_reveal/assets/sounds/__init__.py
ip_reveal/assets/sounds/alerts/__init__.py
ip_reveal/assets/sounds/alerts/blip_pulse.wav
ip_reveal/assets/sounds/alerts/low_pulse.wav
ip_reveal/assets/sounds/alerts/o-pulse-alert.mp3
ip_reveal/assets/sounds/alerts/o-pulse-alert.wav
ip_reveal/assets/sounds/alerts/o-pulse.wav
ip_reveal/assets/sounds/alerts/scifi_pulse.wav
ip_reveal/assets/ui_elements/__init__.py
ip_reveal/assets/ui_elements/backgrounds/__init__.py
ip_reveal/assets/ui_elements/backgrounds/neon_dark.png
ip_reveal/assets/ui_elements/icons/2897337-48.png
ip_reveal/assets/ui_elements/icons/__init__.py
ip_reveal/assets/ui_elements/icons/alerts/__init__.py
ip_reveal/assets/ui_elements/icons/alerts/icons8-warning-shield-40.png
ip_reveal/assets/ui_elements/icons/neon_apply_en_unsel_48x48.png
ip_reveal/assets/ui_elements/icons/neon_main-48.png
ip_reveal/assets/ui_elements/icons/neon_main_16x16.ico
ip_reveal/assets/ui_elements/icons/neon_main_24x24.ico
ip_reveal/assets/ui_elements/icons/neon_main_32x32.ico
ip_reveal/assets/ui_elements/icons/neon_quit_50x50.ico
ip_reveal/assets/ui_elements/icons/neon_quit_92x92.ico
ip_reveal/assets/ui_elements/icons/neon_refresh_50x50.ico
ip_reveal/assets/ui_elements/themes/__init__.py
ip_reveal/config/__init__.py
ip_reveal/config/arguments/__init__.py
ip_reveal/config/errors.py
ip_reveal/gui/__init__.py
ip_reveal/gui/windows/.test.py.swp
ip_reveal/gui/windows/__init__.py
ip_reveal/gui/windows/backgrounds/__init__.py
ip_reveal/gui/windows/preferences.py
ip_reveal/popups/__init__.py
ip_reveal/timers/__init__.py
ip_reveal/tools/__init__.py
ip_reveal/tools/arguments/__init__.py
ip_reveal/tools/logging/__init__.py
ip_reveal/tools/network/__init__.py
ip_reveal/version/__init__.py
ip_reveal/version/VERSION
ip_reveal-1.2.dist-info/entry_points.txt
ip_reveal-1.2.dist-info/WHEEL
ip_reveal-1.2.dist-info/METADATA
ip_reveal-1.2.dist-info/RECORD
