Metadata-Version: 2.1
Name: ip-reveal
Version: 1.2
Summary: A GUI-based widget that checks your IP address periodically, sending notifications if it changes.
License: WTFPL
Author: Taylor B.
Author-email: tayjaybabee@gmail.com
Requires-Python: >=3.7,<4.0
Classifier: License :: Other/Proprietary License
Classifier: Programming Language :: Python :: 3
Classifier: Programming Language :: Python :: 3.7
Classifier: Programming Language :: Python :: 3.8
Classifier: Programming Language :: Python :: 3.9
Requires-Dist: PySimpleGUI (>=4.30.0,<5.0.0)
Requires-Dist: PySimpleGUIQt (>=0.35.0,<0.36.0)
Requires-Dist: humanize (>=3.1.0,<4.0.0)
Requires-Dist: inspy_logger (==2.1a14)
Requires-Dist: inspyre-toolbox (==1.0a7)
Requires-Dist: inspyred_print (>=1.0,<2.0)
Requires-Dist: pypattyrn (>=1.2,<2.0)
Requires-Dist: requests (>=2.25.0,<3.0.0)
Requires-Dist: simpleaudio (>=1.0.4,<2.0.0)
